prismarine/cli.py
prismarine/model.mako
prismarine/prisma_client.py
prismarine/prisma_common.py
prismarine/prisma_easysam.py
prismarine/runtime/__init__.py
prismarine/runtime/cluster.py
prismarine/runtime/dynamo_access.py
prismarine/runtime/dynamo_crud.py
prismarine/runtime/dynamo_default.py
prismarine-1.4.1.dist-info/METADATA
prismarine-1.4.1.dist-info/WHEEL
prismarine-1.4.1.dist-info/entry_points.txt
prismarine-1.4.1.dist-info/licenses/LICENSE
prismarine-1.4.1.dist-info/RECORD
