Metadata-Version: 2.4
Name: prismarine
Version: 1.4.1
Summary: Pythonic DynamoDB ORM
Project-URL: Homepage, https://github.com/adsight-app/prismarine
Project-URL: Changelog, https://github.com/adsight-app/prismarine/blob/main/CHANGELOG.md
License-File: LICENSE
Requires-Python: >=3.12
Requires-Dist: boto3>=1.38.19
Requires-Dist: case-converter>=1.2.0
Requires-Dist: click>=8.2.0
Requires-Dist: gray-formatter>=3.0.10
Requires-Dist: mako>=1.3.10
Requires-Dist: types-boto3[dynamodb]>=1.38.19
